Metadata-Version: 2.1
Name: alex_max_tools
Version: 0.1
Summary: Личные инструменты
Author-email: alexmax11@icloud.com
